fsl_sub_plugin_sge/__init__.py
fsl_sub_plugin_sge/fsl_sub_sge.yml
fsl_sub_plugin_sge/version.py
fsl_sub_plugin_sge/tests/__init__.py
fsl_sub_plugin_sge/tests/test_fsl_sub_plugin_sge.py
fsl_sub_plugin_sge-1.5.5.dist-info/LICENSE
fsl_sub_plugin_sge-1.5.5.dist-info/METADATA
fsl_sub_plugin_sge-1.5.5.dist-info/WHEEL
fsl_sub_plugin_sge-1.5.5.dist-info/top_level.txt
fsl_sub_plugin_sge-1.5.5.dist-info/RECORD
