Metadata-Version: 2.1
Name: fsl_sub_plugin_sge
Version: 1.5.5
Summary: FSL Cluster Submission Plugin for Son of/Univa Grid Engine
Home-page: https://git.fmrib.ox.ac.uk/fsl/fsl_sub_plugin_sge
Author: Duncan Mortimer
Author-email: duncan.mortimer@ndcn.ox.ac.uk
License: Apache License Version 2.0
Project-URL: Documentation, https://fsl.fmrib.ox.ac.uk/fsl/fslwiki
Project-URL: Source, https://git.fmrib.ox.ac.uk/fsl/fsl_sub_plugin_sge
Keywords: FSL fsl Neuroimaging neuroimaging cluster grid slurm grid engine
Classifier: Development Status :: 5 - Production/Stable
Classifier: Intended Audience :: Science/Research
Classifier: Topic :: Scientific/Engineering :: Medical Science Apps.
Classifier: License :: OSI Approved :: Apache Software License
Classifier: Programming Language :: Python :: 3.7
Classifier: Programming Language :: Python :: 3.8
Classifier: Programming Language :: Python :: 3.9
Classifier: Programming Language :: Python :: 3.10
Classifier: Programming Language :: Python :: 3.11
Classifier: Programming Language :: Python :: 3.12
Classifier: Natural Language :: English
Classifier: Environment :: Console
Classifier: Operating System :: MacOS :: MacOS X
Classifier: Operating System :: POSIX :: Linux
Requires-Python: ~=3.7
License-File: LICENSE
Requires-Dist: fsl-sub >=2.7.0
Requires-Dist: ruamel.yaml >=0.16.7
